good_soup/__init__.py
good_soup/cli.py
good_soup/soup.py
good_soup-0.0.1.dist-info/licenses/LICENSE
good_soup-0.0.1.dist-info/METADATA
good_soup-0.0.1.dist-info/WHEEL
good_soup-0.0.1.dist-info/top_level.txt
good_soup-0.0.1.dist-info/RECORD
