Metadata-Version: 2.4
Name: good-soup
Version: 0.0.1
Summary: A tool for making model souping ultra-simple, easy and fast!
Author-email: Bhavnick Minhas <bhavnick@chonkie.ai>
License: Apache 2.0
Project-URL: Bug Tracker, https://github.com/chonkie-inc/good-soup/issues
Project-URL: Source Code, https://github.com/chonkie-inc/good-soup
Keywords: model souping,merging,llm
Classifier: Development Status :: 3 - Alpha
Classifier: Intended Audience :: Developers
Classifier: License :: OSI Approved :: Apache Software License
Classifier: Programming Language :: Python :: 3.10
Classifier: Programming Language :: Python :: 3.11
Classifier: Programming Language :: Python :: 3.12
Classifier: Programming Language :: Python :: 3.13
Requires-Python: >=3.10
License-File: LICENSE
Requires-Dist: transformers>=4.25.0
Requires-Dist: torch>=2.0.0
Requires-Dist: accelerate>=0.20.0
Provides-Extra: dev
Requires-Dist: pytest; extra == "dev"
Requires-Dist: pytest-cov; extra == "dev"
Requires-Dist: pytest-xdist; extra == "dev"
Requires-Dist: ruff; extra == "dev"
Requires-Dist: mypy; extra == "dev"
Dynamic: license-file
